auto_agentic/__init__.py
auto_agentic/agent.py
auto_agentic/config.py
auto_agentic/database_backends.py
auto_agentic/interfaces.py
auto_agentic/llm_providers.py
auto_agentic/memory_backends.py
auto_agentic-0.1.1.dist-info/licenses/LICENSE
auto_agentic-0.1.1.dist-info/METADATA
auto_agentic-0.1.1.dist-info/WHEEL
auto_agentic-0.1.1.dist-info/top_level.txt
auto_agentic-0.1.1.dist-info/RECORD
